sh3ll/PB.py
sh3ll/__init__.py
sh3ll/__main__.py
sh3ll/command.py
sh3ll/ctx.py
sh3ll/sample.py
sh3ll-1.2.2.dist-info/METADATA
sh3ll-1.2.2.dist-info/WHEEL
sh3ll-1.2.2.dist-info/entry_points.txt
sh3ll-1.2.2.dist-info/top_level.txt
sh3ll-1.2.2.dist-info/RECORD
