Metadata-Version: 2.1
Name: sh3ll
Version: 1.2.2
Summary: An interactive shell application maker
Home-page: https://github.com/HullaBrian/sh3ll.git
Author: HullaBrian
Author-email: 
License: UNKNOWN
Platform: UNKNOWN
Requires-Dist: art
